{
    "next_update_time": 1744973207,
    "users": {
        "306": "Тохтаназарова Хадича",
        "218": "Humoyun Toirjonov",
        "215": "Behruz Abdullazizov",
        "217": "Albina Toksanbayeva",
        "150": "Elyor",
        "307": "Sharifjon Solijonov",
        "210": "Мадина Юлдашова",
        "214": "Sanjar Sattorov",
        "304": "Ibrohim Tursunboyev",
        "223": "Nodir Nazarov",
        "219": "Jafar Xayrullayev",
        "203": "Madina Ruziyeva",
        "225": "Intizor Bahtiyorova",
        "302": "Shaxzodbek Qahramonov",
        "220": "Izzatullayev Jamshid",
        "201": "Suroj",
        "301": "Sanjar Egamberdiyev",
        "212": "Suhrob Nuriddinov",
        "211": "Sohib Bazaraliyev",
        "305": "Zohid Muhammadiev"
    }
}